{"cameraMode":{"drawMode":0,"name":"Shaded","section":"Shading Mode"},"sceneLighting":true,"audioPlay":false,"sceneViewState":{"m_AlwaysRefresh":false,"showFog":true,"showSkybox":true,"showFlares":true,"showImageEffects":true,"showParticleSystems":true,"showVisualEffectGraphs":true,"m_FxEnabled":true},"in2DMode":false,"pivot":{"x":-5.945150852203369,"y":0.7000541687011719,"z":1.396051287651062},"rotation":{"x":0.0738045945763588,"y":-0.7113937735557556,"z":0.08326860517263413,"w":0.6947611570358276},"size":1.5094287395477296,"orthographic":false}